netpyne/__init__.py
netpyne/analysis/__init__.py
netpyne/analysis/csd.py
netpyne/analysis/dipole.py
netpyne/analysis/filter.py
netpyne/analysis/info.py
netpyne/analysis/interactive.py
netpyne/analysis/lfp.py
netpyne/analysis/lfp_orig.py
netpyne/analysis/mapping.py
netpyne/analysis/network.py
netpyne/analysis/rxd.py
netpyne/analysis/spikes.py
netpyne/analysis/spikes_legacy.py
netpyne/analysis/tools.py
netpyne/analysis/traces.py
netpyne/analysis/utils.py
netpyne/analysis/wrapper.py
netpyne/batch/__init__.py
netpyne/batch/asd_parallel.py
netpyne/batch/batch.py
netpyne/batch/evol.py
netpyne/batch/grid.py
netpyne/batch/optuna_parallel.py
netpyne/batch/sbi_parallel.py
netpyne/batch/utils.py
netpyne/batchtools/__init__.py
netpyne/batchtools/analysis.py
netpyne/batchtools/comm.py
netpyne/batchtools/evol.py
netpyne/batchtools/header.py
netpyne/batchtools/runners.py
netpyne/batchtools/search.py
netpyne/batchtools/submits.py
netpyne/cell/NML2Cell.py
netpyne/cell/NML2SpikeSource.py
netpyne/cell/__init__.py
netpyne/cell/cell.py
netpyne/cell/compartCell.py
netpyne/cell/inputs.py
netpyne/cell/pointCell.py
netpyne/conversion/__init__.py
netpyne/conversion/excel.py
netpyne/conversion/neuromlFormat.py
netpyne/conversion/neuronPyHoc.py
netpyne/conversion/pythonScript.py
netpyne/conversion/sonataImport.py
netpyne/metadata/__init__.py
netpyne/metadata/api.py
netpyne/metadata/metadata.py
netpyne/network/__init__.py
netpyne/network/conn.py
netpyne/network/modify.py
netpyne/network/netrxd.py
netpyne/network/network.py
netpyne/network/pop.py
netpyne/network/shape.py
netpyne/network/stim.py
netpyne/network/subconn.py
netpyne/plotting/__init__.py
netpyne/plotting/plotCSD.py
netpyne/plotting/plotLFPLocations.py
netpyne/plotting/plotLFPSpectrogram.py
netpyne/plotting/plotRaster.py
netpyne/plotting/plotShape.py
netpyne/plotting/plotSpikeFreq.py
netpyne/plotting/plotSpikeHist.py
netpyne/plotting/plotTimeSeries.py
netpyne/plotting/plotTimeSeriesPSD.py
netpyne/plotting/plotter.py
netpyne-1.1.1.dist-info/LICENSE
netpyne-1.1.1.dist-info/METADATA
netpyne-1.1.1.dist-info/WHEEL
netpyne-1.1.1.dist-info/top_level.txt
netpyne-1.1.1.dist-info/RECORD
