Metadata-Version: 2.1
Name: netpyne
Version: 1.1.1
Summary: A Python package to develop, simulate and analyse biological neuronal networks in NEURON.
Home-page: https://github.com/Neurosim-lab/netpyne
Author: Salvador Dura-Bernal (Neurosim lab)
Author-email: salvadordura@gmail.com
License: MIT
Keywords: neuron,network,developing,framework,biological,simulation
Classifier: Development Status :: 4 - Beta
Classifier: Intended Audience :: Science/Research
Classifier: Topic :: Scientific/Engineering :: Visualization
Classifier: License :: OSI Approved :: MIT License
Classifier: Programming Language :: Python :: 3
Classifier: Programming Language :: Python :: 3.7
Classifier: Programming Language :: Python :: 3.8
Classifier: Programming Language :: Python :: 3.9
Classifier: Programming Language :: Python :: 3.10
Classifier: Programming Language :: Python :: 3.11
License-File: LICENSE
Requires-Dist: numpy
Requires-Dist: scipy
Requires-Dist: matplotlib
Requires-Dist: matplotlib-scalebar
Requires-Dist: future
Requires-Dist: pandas
Requires-Dist: bokeh
Requires-Dist: schema
Requires-Dist: lfpykit
Requires-Dist: tqdm
